url_validatorIndx/__init__.py
url_validatorIndx/function.py
url_validatorIndx-1.1.4.dist-info/LICENCE.txt
url_validatorIndx-1.1.4.dist-info/METADATA
url_validatorIndx-1.1.4.dist-info/WHEEL
url_validatorIndx-1.1.4.dist-info/top_level.txt
url_validatorIndx-1.1.4.dist-info/RECORD
