Metadata-Version: 2.1
Name: url_validatorIndx
Version: 1.1.4
Summary: Testing installation of Package
Author: Rishabh K
Author-email: rshb.kapoor@gmail.com
License: MIT
Keywords: pypi,url_validatorIndx,tutorial
Classifier: Development Status :: 3 - Alpha
Classifier: Intended Audience :: Developers
Classifier: Topic :: Software Development :: Documentation
Classifier: License :: OSI Approved :: MIT License
Classifier: Programming Language :: Python :: 3
Classifier: Programming Language :: Python :: 3.7
Classifier: Programming Language :: Python :: 3.8
Classifier: Programming Language :: Python :: 3.9
License-File: LICENCE.txt
